rtl_reference/conv3x3_mac_pair.v
`timescale 1ns / 1ps
//===========================================================================
//  conv3x3_mac_pair
//
//  Two int8 multiplications that share one activation operand.  This is the
//  pairing reported in Section V-B of
//
//      "An Ethernet Instruction-Driven INT8 FPGA NPU for Single-Stage
//       Multi-Person Pose Estimation"
//
//  The deployed engine folds such a pair onto a single DSP48E1, and a
//  sign-correction constant keeps the even-lane product exact whenever the
//  odd-lane product is negative.  A zero activation produces no borrow for
//  that constant to cancel, so the even-lane product then comes out one
//  larger.  That is the packed-DSP artifact the paper reports, and the model
//  below reproduces it rather than hiding it, because the compiler's golden
//  reproduces it too.
//
//  Reference model.  It states the arithmetic that the paper describes; it is
//  not the deployed source and does not model a vendor primitive.
//===========================================================================
module conv3x3_mac_pair #(
    parameter integer LATENCY = 5      // registered stages before the output
)(
    input  wire               clk,
    input  wire               rst,
    input  wire signed [7:0]  coef_even,
    input  wire signed [7:0]  coef_odd,
    input  wire        [7:0]  act,      // activations are unsigned bytes
    output wire signed [15:0] prod_even,
    output wire signed [15:0] prod_odd
);

    // an unsigned activation promoted to a positive signed operand
    wire signed [8:0] act_s = $signed({1'b0, act});

    // the artifact: it appears only when the shared operand is zero and the
    // odd-lane coefficient is negative
    wire correction = (act == 8'd0) & coef_odd[7];

    wire signed [17:0] wide_even = coef_even * act_s + $signed({17'd0, correction});
    wire signed [17:0] wide_odd  = coef_odd  * act_s;

    // |coef| <= 128 and act <= 255 bound both products to [-32640, 32385],
    // so sixteen bits carry them without loss.
    reg signed [15:0] delay_even [0:LATENCY-1];
    reg signed [15:0] delay_odd  [0:LATENCY-1];

    integer stage;
    always @(posedge clk) begin
        if (rst) begin
            for (stage = 0; stage < LATENCY; stage = stage + 1) begin
                delay_even[stage] <= 16'sd0;
                delay_odd [stage] <= 16'sd0;
            end
        end else begin
            delay_even[0] <= wide_even[15:0];
            delay_odd [0] <= wide_odd [15:0];
            for (stage = 1; stage < LATENCY; stage = stage + 1) begin
                delay_even[stage] <= delay_even[stage-1];
                delay_odd [stage] <= delay_odd [stage-1];
            end
        end
    end

    assign prod_even = delay_even[LATENCY-1];
    assign prod_odd  = delay_odd [LATENCY-1];

endmodule

rtl_reference/conv3x3_mac_array.v
`timescale 1ns / 1ps
//===========================================================================
//  conv3x3_mac_array
//
//  Reference model of the 3x3 convolution multiply-accumulate array of
//
//      "An Ethernet Instruction-Driven INT8 FPGA NPU for Single-Stage
//       Multi-Person Pose Estimation"          (Section IV-A, Fig. 5)
//
//  Every cycle the array performs
//
//      TAPS x LANES x SLICES = 9 x 16 x 8 = 1152
//
//  int8 multiply-accumulates: the nine taps of a 3x3 kernel, sixteen input
//  channels -- one NHWC-16 word -- and eight output channels, all unrolled in
//  the same cycle.  Feature-map rows and columns are not unrolled.  The three
//  rows of the window arrive together, one NHWC-16 word each; the three
//  columns are formed inside from three consecutive beats of that stream.
//
//  The reduction runs across the taps first and across the input channels
//  afterwards.  Integer addition is associative and the accumulator here is
//  wide enough to be lossless, so how the summation is split into pipeline
//  stages is an implementation choice and not a numerical one; this model
//  sums the nine taps of a lane in one stage and then folds the sixteen lane
//  sums with a balanced binary tree.
//
//  Accumulator width.  One product is bounded by 128*255 = 32640; the array
//  sums TAPS*LANES = 144 of them and can add up to 144 packed-DSP correction
//  terms, so |result| <= 4,700,304 < 2^23 and a flat 24-bit signed
//  accumulator is lossless at every stage of this model.  Accumulation across
//  several NHWC-16 words, which the deployed engine performs downstream, is
//  outside this model.
//
//  Interface contract.
//    * A coefficient burst is exactly SLICES contiguous beats, one per output
//      channel.  A gap in coef_we restarts the burst at output channel 0.
//    * Coefficients must not be reloaded while an activation stream is in
//      flight: this model holds one coefficient set, not a shadow buffer.
//    * row_delay advances only while pix_we is high, so a gap in the
//      activation stream stalls the window instead of corrupting it.
//    * psum_we marks a sample whose three-column window lies entirely inside
//      the stream; the first two samples after a stream starts are masked.
//
//  Scope.  This file models the arithmetic and the dataflow that the paper
//  describes for the 3x3 engine.  Line buffering, DDR-side addressing,
//  coefficient double buffering, requantization, and the 1x1 engine that
//  shares the same packed-multiplier scheme are not part of this model.
//  Its self-check is tb_mac_selfcheck.v and the captured run is in sim/.
//===========================================================================
module conv3x3_mac_array #(
    parameter integer TAPS    = 9,     // 3x3 kernel, tap index = row*3 + col
    parameter integer LANES   = 16,    // input channels per NHWC-16 word
    parameter integer SLICES  = 8,     // output channels computed together
    parameter integer ACC_W   = 24,    // lossless accumulator width
    parameter integer MUL_LAT = 5      // pipeline depth of one multiplier pair
)(
    input  wire clk,
    input  wire rst,

    // ---- coefficient load: one beat per output channel, SLICES beats -----
    // Beat layout is lane-major: byte (lane*TAPS + tap) is the coefficient of
    // that tap and that input channel for the output channel being loaded.
    input  wire                        coef_we,
    input  wire [TAPS*LANES*8-1:0]     coef_beat,

    // ---- activation stream: the three rows of the window, one word each --
    // Row-major: byte (row*LANES + lane).
    input  wire                        pix_we,
    input  wire [3*LANES*8-1:0]        pix_rows,

    // ---- partial sums, one per output channel ---------------------------
    output wire signed [ACC_W-1:0]     psum_0,
    output wire signed [ACC_W-1:0]     psum_1,
    output wire signed [ACC_W-1:0]     psum_2,
    output wire signed [ACC_W-1:0]     psum_3,
    output wire signed [ACC_W-1:0]     psum_4,
    output wire signed [ACC_W-1:0]     psum_5,
    output wire signed [ACC_W-1:0]     psum_6,
    output wire signed [ACC_W-1:0]     psum_7,
    output wire                        psum_we
);

    localparam integer COLS       = 3;
    localparam integer TREE_DEPTH = 4;      // log2(LANES)

    // registered stages from pix_rows to the outputs:
    //   window register 1 + multiplier pair MUL_LAT + tap sum 1 + tree stages
    localparam integer LATENCY = 1 + MUL_LAT + 1 + TREE_DEPTH;

    genvar t, l, s, p, n;

    // =====================================================================
    //  coefficient store
    //  One byte per (slice, lane, tap).  The beat counter restarts at zero
    //  whenever the burst is not active, so a burst always begins at output
    //  channel 0.
    // =====================================================================
    reg [7:0]              coef_mem [0:SLICES-1][0:LANES-1][0:TAPS-1];
    reg [$clog2(SLICES):0] beat_idx;

    integer li, ti;
    always @(posedge clk) begin
        if (rst || !coef_we) begin
            beat_idx <= 0;
        end else begin
            for (li = 0; li < LANES; li = li + 1)
                for (ti = 0; ti < TAPS; ti = ti + 1)
                    coef_mem[beat_idx][li][ti] <=
                        coef_beat[(li*TAPS + ti)*8 +: 8];
            beat_idx <= (beat_idx == SLICES-1) ? 0 : beat_idx + 1;
        end
    end

    // =====================================================================
    //  window formation
    //  The three rows arrive together; the three columns are the newest three
    //  beats of that stream, column 0 being the oldest.
    // =====================================================================
    reg [LANES*8-1:0] row_delay [0:COLS-1][0:COLS-1];     // [row][age]

    integer ri, ai;
    always @(posedge clk) begin
        if (rst) begin
            for (ri = 0; ri < COLS; ri = ri + 1)
                for (ai = 0; ai < COLS; ai = ai + 1)
                    row_delay[ri][ai] <= {(LANES*8){1'b0}};
        end else if (pix_we) begin
            for (ri = 0; ri < COLS; ri = ri + 1) begin
                for (ai = COLS-1; ai > 0; ai = ai - 1)
                    row_delay[ri][ai] <= row_delay[ri][ai-1];
                row_delay[ri][0] <= pix_rows[ri*LANES*8 +: LANES*8];
            end
        end
    end

    // tap t = row*3 + col, and column 0 is the oldest beat, i.e. age COLS-1-col
    wire [7:0] act_of [0:TAPS-1][0:LANES-1];
    generate
        for (t = 0; t < TAPS; t = t + 1) begin : TAP_ACT
            localparam integer TR = t / COLS;
            localparam integer TC = t % COLS;
            for (l = 0; l < LANES; l = l + 1) begin : TAP_ACT_LANE
                assign act_of[t][l] = row_delay[TR][COLS-1-TC][l*8 +: 8];
            end
        end
    endgenerate

    // =====================================================================
    //  the 1152 multipliers
    //  Output channels are taken two at a time; the pair shares its
    //  activation operand.
    // =====================================================================
    wire signed [15:0] prod [0:TAPS-1][0:LANES-1][0:SLICES-1];

    generate
        for (t = 0; t < TAPS; t = t + 1) begin : MUL_TAP
            for (l = 0; l < LANES; l = l + 1) begin : MUL_LANE
                for (p = 0; p < SLICES/2; p = p + 1) begin : MUL_PAIR
                    conv3x3_mac_pair #(.LATENCY(MUL_LAT)) u_pair (
                        .clk       (clk),
                        .rst       (rst),
                        .coef_even (coef_mem[p*2  ][l][t]),
                        .coef_odd  (coef_mem[p*2+1][l][t]),
                        .act       (act_of[t][l]),
                        .prod_even (prod[t][l][p*2  ]),
                        .prod_odd  (prod[t][l][p*2+1])
                    );
                end
            end
        end
    endgenerate

    // =====================================================================
    //  reduction, taps first
    // =====================================================================
    reg signed [ACC_W-1:0] lane_sum [0:SLICES-1][0:LANES-1];

    generate
        for (s = 0; s < SLICES; s = s + 1) begin : TAPSUM_SLICE
            for (l = 0; l < LANES; l = l + 1) begin : TAPSUM_LANE
                integer k;
                reg signed [ACC_W-1:0] acc;
                always @(posedge clk) begin
                    if (rst) begin
                        lane_sum[s][l] <= {ACC_W{1'b0}};
                    end else begin
                        acc = {ACC_W{1'b0}};
                        for (k = 0; k < TAPS; k = k + 1)
                            acc = acc + $signed(prod[k][l][s]);
                        lane_sum[s][l] <= acc;
                    end
                end
            end
        end
    endgenerate

    // =====================================================================
    //  reduction, input channels afterwards: a balanced binary tree
    // =====================================================================
    reg signed [ACC_W-1:0] tree [0:TREE_DEPTH-1][0:SLICES-1][0:LANES/2-1];

    generate
        for (s = 0; s < SLICES; s = s + 1) begin : TREE_SLICE
            for (t = 0; t < TREE_DEPTH; t = t + 1) begin : TREE_STAGE
                localparam integer NODES = LANES >> (t + 1);
                for (n = 0; n < NODES; n = n + 1) begin : TREE_NODE
                    if (t == 0) begin : FROM_LANES
                        always @(posedge clk)
                            if (rst) tree[0][s][n] <= {ACC_W{1'b0}};
                            else     tree[0][s][n] <= $signed(lane_sum[s][n*2])
                                                    + $signed(lane_sum[s][n*2+1]);
                    end else begin : FROM_TREE
                        always @(posedge clk)
                            if (rst) tree[t][s][n] <= {ACC_W{1'b0}};
                            else     tree[t][s][n] <= $signed(tree[t-1][s][n*2])
                                                    + $signed(tree[t-1][s][n*2+1]);
                    end
                end
            end
        end
    endgenerate

    // =====================================================================
    //  output valid
    //  The array is a fixed-latency pipeline, so the strobe is the accepted
    //  activation beat delayed by LATENCY.  A window spans three consecutive
    //  beats, so a sample counts only if the beat two positions earlier was
    //  also accepted; that masks the two head samples of every stream.
    // =====================================================================
    reg [LATENCY+1:0] we_pipe;
    always @(posedge clk) begin
        if (rst) we_pipe <= {(LATENCY+2){1'b0}};
        else     we_pipe <= {we_pipe[LATENCY:0], pix_we};
    end

    assign psum_0  = tree[TREE_DEPTH-1][0][0];
    assign psum_1  = tree[TREE_DEPTH-1][1][0];
    assign psum_2  = tree[TREE_DEPTH-1][2][0];
    assign psum_3  = tree[TREE_DEPTH-1][3][0];
    assign psum_4  = tree[TREE_DEPTH-1][4][0];
    assign psum_5  = tree[TREE_DEPTH-1][5][0];
    assign psum_6  = tree[TREE_DEPTH-1][6][0];
    assign psum_7  = tree[TREE_DEPTH-1][7][0];
    assign psum_we = we_pipe[LATENCY-1] & we_pipe[LATENCY+1];

endmodule

rtl_reference/tb_mac_selfcheck.v
`timescale 1ns / 1ps
//===========================================================================
//  tb_mac_selfcheck -- self-checking testbench for conv3x3_mac_array
//
//  The expected partial sums are computed independently, with a plain nested
//  loop over the nine taps and the sixteen input channels, so the model is
//  checked against the arithmetic the paper states and not against another
//  copy of the same RTL.
//
//  Results are latched the way a consumer would latch them, on psum_we, so
//  the strobe has to be aligned with the data it labels; capturing every
//  cycle instead would hide a misplaced valid.
//
//  Stimulus phases:
//    A  random coefficients and random activations, about a third of the
//       activation bytes forced to zero
//    B  an all-zero activation word, which isolates the packed-multiplier
//       artifact: an even-lane output is then exactly the number of negative
//       odd-lane coefficients paired with it
//    C  the extremes, coefficient -128 and +127 against activations 0 and 255
//
//  All stimulus is applied on the falling edge, so nothing the array samples
//  changes in the same time step as the sampling edge.
//
//  Run:
//    xvlog -sv conv3x3_mac_pair.v conv3x3_mac_array.v tb_mac_selfcheck.v
//    xelab --debug off --relax -L work --snapshot macref work.tb_mac_selfcheck
//    xsim macref -R
//===========================================================================
module tb_mac_selfcheck;

    localparam integer TAPS   = 9;
    localparam integer LANES  = 16;
    localparam integer SLICES = 8;
    localparam integer COLS   = 3;
    localparam integer NDRIVE = 560;

    reg clk = 1'b0;
    reg rst = 1'b1;
    always #5 clk = ~clk;

    // ---------------- device under test ---------------------------------
    reg                     coef_we = 1'b0;
    reg  [TAPS*LANES*8-1:0] coef_beat;
    reg                     pix_we  = 1'b0;
    reg  [3*LANES*8-1:0]    pix_rows;

    wire signed [23:0] psum_0, psum_1, psum_2, psum_3;
    wire signed [23:0] psum_4, psum_5, psum_6, psum_7;
    wire               psum_we;

    conv3x3_mac_array u_dut (
        .clk(clk), .rst(rst),
        .coef_we(coef_we), .coef_beat(coef_beat),
        .pix_we(pix_we),   .pix_rows(pix_rows),
        .psum_0(psum_0), .psum_1(psum_1), .psum_2(psum_2), .psum_3(psum_3),
        .psum_4(psum_4), .psum_5(psum_5), .psum_6(psum_6), .psum_7(psum_7),
        .psum_we(psum_we)
    );

    // ---------------- stimulus and independent golden -------------------
    reg  [7:0]   coef     [0:TAPS-1][0:LANES-1][0:SLICES-1];
    reg  [7:0]   hist     [0:NDRIVE-1][0:COLS-1][0:LANES-1];
    reg  [191:0] expect_q [0:NDRIVE-1];
    reg  [191:0] latched  [0:NDRIVE-1];
    integer      n_expect = 0;
    integer      n_latch  = 0;

    integer t, l, s, i, j, c, r;
    integer seed = 32'h0BADC0DE;
    reg signed [23:0] acc;
    reg signed [23:0] gold [0:SLICES-1];
    reg        [7:0]  a_byte;
    reg signed [7:0]  c_even, c_odd;
    integer zero_bytes = 0, artifact_terms = 0;

    // latch exactly as a consumer would: on the strobe
    always @(posedge clk) begin
        if (!rst && psum_we && n_latch < NDRIVE) begin
            latched[n_latch] <= {psum_7, psum_6, psum_5, psum_4,
                                 psum_3, psum_2, psum_1, psum_0};
            n_latch          <= n_latch + 1;
        end
    end

    // window n takes column c of every row from beat n-3+c, column 0 oldest
    task compute_golden(input integer n);
        begin
            for (s = 0; s < SLICES; s = s + 1) begin
                acc = 24'sd0;
                for (t = 0; t < TAPS; t = t + 1) begin
                    r = t / COLS;
                    c = t % COLS;
                    for (l = 0; l < LANES; l = l + 1) begin
                        a_byte = hist[n-3+c][r][l];
                        c_even = coef[t][l][s];
                        acc = acc + $signed(c_even) * $signed({1'b0, a_byte});
                        if (s % 2 == 0) begin
                            c_odd = coef[t][l][s+1];
                            if (a_byte == 8'd0 && c_odd[7]) begin
                                acc = acc + 24'sd1;
                                artifact_terms = artifact_terms + 1;
                            end
                        end
                    end
                end
                gold[s] = acc;
            end
            expect_q[n_expect] = {gold[7], gold[6], gold[5], gold[4],
                                  gold[3], gold[2], gold[1], gold[0]};
            n_expect = n_expect + 1;
        end
    endtask

    task load_coefficients;
        integer ss, ll, tt;
        begin
            for (ss = 0; ss < SLICES; ss = ss + 1) begin
                @(negedge clk);
                for (ll = 0; ll < LANES; ll = ll + 1)
                    for (tt = 0; tt < TAPS; tt = tt + 1)
                        coef_beat[(ll*TAPS + tt)*8 +: 8] = coef[tt][ll][ss];
                coef_we = 1'b1;
            end
            @(negedge clk);
            coef_we = 1'b0;
        end
    endtask

    // ---------------- main ----------------------------------------------
    integer mismatches, compared, k;

    initial begin
        // the interface signals only, so the dump stays small enough to ship
        $dumpfile("mac_array.vcd");
        $dumpvars(1, tb_mac_selfcheck);

        for (t = 0; t < TAPS; t = t + 1)
            for (l = 0; l < LANES; l = l + 1)
                for (s = 0; s < SLICES; s = s + 1)
                    coef[t][l][s] = $random(seed);
        // phase C pins the coefficient extremes on the first four lanes
        for (t = 0; t < TAPS; t = t + 1)
            for (l = 0; l < 4; l = l + 1) begin
                coef[t][l][0] =  8'sd127;
                coef[t][l][1] = -8'sd128;
                coef[t][l][2] = -8'sd128;
                coef[t][l][3] =  8'sd127;
            end

        for (i = 0; i < NDRIVE; i = i + 1)
            for (j = 0; j < COLS; j = j + 1)
                for (l = 0; l < LANES; l = l + 1) begin
                    if (i >= 200 && i < 240)
                        hist[i][j][l] = 8'd0;
                    else if (i >= 300 && i < 340)
                        hist[i][j][l] = (l % 2) ? 8'd255 : 8'd0;
                    else if ((($random(seed) % 10) + 10) % 10 < 3)
                        hist[i][j][l] = 8'd0;
                    else
                        hist[i][j][l] = $random(seed);
                    if (hist[i][j][l] == 8'd0) zero_bytes = zero_bytes + 1;
                end

        repeat (6) @(posedge clk);
        @(negedge clk);
        rst = 1'b0;

        load_coefficients;
        repeat (3) @(negedge clk);

        for (i = 0; i < NDRIVE; i = i + 1) begin
            @(negedge clk);
            for (j = 0; j < COLS; j = j + 1)
                for (l = 0; l < LANES; l = l + 1)
                    pix_rows[(j*LANES + l)*8 +: 8] = hist[i][j][l];
            pix_we = 1'b1;
            if (i >= 3) compute_golden(i);
        end
        @(negedge clk);
        pix_we = 1'b0;
        // the last window closes on the final beat, one beyond the loop
        compute_golden(NDRIVE);
        repeat (30) @(posedge clk);

        // the strobe must label the sample it accompanies, so the latched
        // sequence is compared position by position with no realignment
        mismatches = 0;
        compared = (n_latch < n_expect) ? n_latch : n_expect;
        for (k = 0; k < compared; k = k + 1)
            if (expect_q[k] !== latched[k]) begin
                if (mismatches < 5)
                    $display("  MISMATCH at strobe %0d: expected %h latched %h",
                             k, expect_q[k], latched[k]);
                mismatches = mismatches + 1;
            end

        $display("");
        $display("=========================================================");
        $display("  conv3x3_mac_array -- self-check against an independent");
        $display("  nested-loop model of the arithmetic stated in the paper");
        $display("---------------------------------------------------------");
        $display("  multiply-accumulates per cycle : %0d", TAPS*LANES*SLICES);
        $display("  activation beats driven        : %0d", NDRIVE);
        $display("  complete windows expected      : %0d", n_expect);
        $display("  psum_we strobes observed       : %0d", n_latch);
        $display("  samples compared               : %0d", compared);
        $display("  zero activation bytes driven   : %0d", zero_bytes);
        $display("  packed-DSP artifact terms      : %0d", artifact_terms);
        $display("  MISMATCHES                     : %0d", mismatches);
        if (mismatches == 0 && n_latch == n_expect && compared > 400)
            $display("  RESULT: PASS");
        else
            $display("  RESULT: FAIL");
        $display("=========================================================");
        $finish;
    end

endmodule

rtl_reference/sim/mac_array.vcd
$date
   Fri Sep  4 16:56:08 2026
$end
$version
  2019.2
$end
$timescale
  1ps
$end
$scope module tb_mac_selfcheck $end
$var reg 1 ! clk $end
$var reg 1 " rst $end
$var reg 1 # coef_we $end
$var reg 1152 $ coef_beat [1151:0] $end
$var reg 1 % pix_we $end
$var reg 384 & pix_rows [383:0] $end
$var wire 24 ' psum_0 [23:0] $end
$var wire 24 ( psum_1 [23:0] $end
$var wire 24 ) psum_2 [23:0] $end
$var wire 24 * psum_3 [23:0] $end
$var wire 24 + psum_4 [23:0] $end
$var wire 24 , psum_5 [23:0] $end
$var wire 24 - psum_6 [23:0] $end
$var wire 24 . psum_7 [23:0] $end
$var wire 1 / psum_we $end
$var integer 32 0 n_expect $end
$var integer 32 1 n_latch $end
$var integer 32 2 t $end
$var integer 32 3 l $end
$var integer 32 4 s $end
$var integer 32 5 i $end
$var integer 32 6 j $end
$var integer 32 7 c $end
$var integer 32 8 r $end
$var integer 32 9 seed $end
$var reg 24 : acc [23:0] $end
$var reg 8 ; a_byte [7:0] $end
$var reg 8 < c_even [7:0] $end
$var reg 8 = c_odd [7:0] $end
$var integer 32 > zero_bytes $end
$var integer 32 ? artifact_terms $end
$var integer 32 @ mismatches $end
$var integer 32 A compared $end
$var integer 32 B k $end
$var parameter 0 C TAPS $end
$var parameter 0 D LANES $end
$var parameter 0 E SLICES $end
$var parameter 0 F COLS $end
$var parameter 0 G NDRIVE $end
$upscope $end
$enddefinitions $end
#0
$dumpvars
0!
1"
0#
bx $
0%
bx &
bx '
bx (
bx )
bx *
bx +
bx ,
bx -
bx .
x/
b0 0
b0 1
b1001 2
b10000 3
b1000 4
b1000110000 5
b11 6
bx 7
bx 8
b11110100011110101101011110110100 9
bx :
bx ;
bx <
bx =
b10011001110010 >
b0 ?
bx @
bx A
bx B
b1001 C
b10000 D
b1000 E
b11 F
b1000110000 G
$end
#5000
1!
b0 '
b0 (
b0 )
b0 *
b0 +
b0 ,
b0 -
b0 .
0/
#10000
0!
#15000
1!
#20000
0!
#25000
1!
#30000
0!
#35000
1!
#40000
0!
#45000
1!
#50000
0!
#55000
1!
#60000
0!
0"
#65000
1!
#70000
0!
1#
b10011100101011011100100100110110010000000010110001000011110011000001000110111010000101110010110101000000100110111000011001001001001010100111001101111100110111000001000001100001000101010111010011000110010101110110101100001011010010111110101100110101011011101101111111010000100011010101011010000111110010110110110010110010111001110100111100110101110111101001010111000011100101110011010011100010111011011001011100101001111011000010101010101101001000100011111101001001100010000100011011001010010111000100001110000110010110000001110100011011100111011110011001000100111111000101011011010110100001001110000100110010110001001101110011000101110000110010000100010110000001101101001111000001000110110010100000110000011111000101010000100111110010011110000110111000100110111100101010010010001110100000101010000010011010101101011000001110010110100000010101010000100010111111100011111110111111101111111011111110111111101111111011111110111111101111111011111110111111101111111011111110111111101111111011111110111111101111111011111110111111101111111011111110111111101111111011111110111111101111111011111110111111101111111011111110111111101111111011111110111111101111111 $
#75000
1!
#80000
0!
b101110011010111000001000100010111100001001010110110110111111110001010010111111011100001010010000000001001011011101001110011000001001110010011001110011001111001101100111110001001011010011001010101100010000001001100101110101001100001100001111010000000001110000100010000000000101010111000111111101010111100100101101100101010110001100110001101000110101001011100011001101000001110010110011100101110110011010111000001110101000010000111010001001111001100100001001000100100100111101010010110111110111011110111110111000010000111000110100111100111111000111010101001101001010111011101110011011101100001111100000011001101111001000101100101010010001101000001110100010101000011111001101000010001101100111011110101101011111111001010111000110101001011010101101111110110010100011011001101000000010111100001110010011100001000001111100001101111100100111101001001101000100000110110100000001000000010000000100000001000000010000000100000001000000010000000100000001000000010000000100000001000000010000000100000001000000010000000100000001000000010000000100000001000000010000000100000001000000010000000100000001000000010000000100000001000000010000000100000001000000010000000 $
#85000
1!
#90000
0!
b100101110011001011011111111001001000001000000000101000001010011001010111101101010000100100111111000111010110010111011101010001110110100000000100001010010110011011001111101001110011000110110011011100011010110110101100101100001010011110001010000111000010001001011111100101111000111100001010111110110010110010000001001111011010010111111101100010001000101101001001111011001001011000010100001010101001110000101110101000111100000101001010101111011110111100011101100010110111110100110111111111100001010110111111111110011010000111100110100010100101001100000101011000110011000100110011011001100110001000010010101110111010000100000111001100100110010111100101101111111110101101011101110110000001111111110111001001000110101010001101010101101010000100111001011000010101111101110110111010100000000011111010100110110000111101010001001001010100110110001111101011110111000010010110100000001000000010000000100000001000000010000000100000001000000010000000100000001000000010000000100000001000000010000000100000001000000010000000100000001000000010000000100000001000000010000000100000001000000010000000100000001000000010000000100000001000000010000000100000001000000010000000 $
#95000
1!
#100000
0!
b101010100111010000101100010010000011100101110101011100001001110101110001100101000100110111111001100010101111010000101101001001111101011100110001111110111010010101011011100100111100000001010101110010001000110000010100110100001010010110111001000000100111001100000000100111100100000011011010010001111000101001011000001001100110100010010001000101010110100100000001111000101011000101101111000011111000011011001000110010010111110111010111111000000000001010001110111110001011010000110110111100100101110011101000000010001011110101110000000101001001110100000000001100000010000111000111110110001010101100100110101111101110011100010100101110010100101100111110000100101010011010100101000001001011011110110010111010010100111111011001101001101000011110110000100100111010011001011100001010001000000011010111000000100111100000101000000001100000011100011110001111110101111101110000011111110111111101111111011111110111111101111111011111110111111101111111011111110111111101111111011111110111111101111111011111110111111101111111011111110111111101111111011111110111111101111111011111110111111101111111011111110111111101111111011111110111111101111111011111110111111101111111 $
#105000
1!
#110000
0!
b11011010010000010100010110101111010010011101100100100110111111010001111011100100111110000101111111100000010001000101010011011000100101100101011110111110110011110101011100011111111011111000110111000010010110010001011110111011001011101010110100000000111100010100001011000010001101100110010101110100111001110110101011000100110000110010011110111100010010001001100010100011000010011111001000101010011101111010000001110001101011000001110010101011011011101001101111111011010100100110110100001111000001000001001011110101000101111111100001100001000101001110000010001010110110101001100011110110001100101111000011111010000101000000101010100101101001101101110000010001111101001000111010101011000010100111101111000011101010101111011100010100001010011001011100101000101001111101100010000100011101110111001110100000100000011101000001011000111000000011000100010000010010101010001100101001101010110010000101010010000010110000111000100111000111011011011111010000001000000101100101000011101001000100011111110101011100011000100011111100101110111100100111101010111010101001000010100010111011010011001110011011000000111000111000000101001011011100110010110000100111100101111 $
#115000
1!
#120000
0!
b111100011001111101000101011101101100011111001011000101100011111011010100001001011011110101010010111110001100001011000101000101011100010111101010110010011110101011100110010011111011101010111011111001101100111100001001100101010001001100100001110100100011101101101110100000011000011110010100111001000001101001101101011100001011100011011000011001011111001000010011110011111110110110001100110000011010000000111100101010101111111001001011100111101111100000010001011111001100111110011101011110011111100110101111100111011111111000110010010100000110100110010010111000000110011000111000010100100100101000000011000100010000100101111110000001010011001010010111000100110100011100000010010101110101101100100010110000000100100011001111111110000111010000010011011010110000111010010010100010011000100000100100001100111011011111010100100111100010101010001010110101000001101101110100110001010001011101010000000000101100010000101000110000100010011111101010100011111100101100010011011110100001010111111000001101101110010000010110110011011011001110100011001100001110110101110000010010110001010001011101111001000010110001010011011010111000101011000011001010111101010011010100 $
#125000
1!
#130000
0!
b111101111011011010011101001011111111000101100110000100110111101100100011111100001100101101000001010101110001000101110010100000000011110110101110000001100110001111001000101110011011101001001111111111000100010110101101100110000011010100111111101110101010100000001111111100100101011000111101110010011100111010011011101101011001111111011110111101010110100110111101010101110110000010000110110011010011100011001101100011010111111110100101010001010111011100010011100110111001010110000100111010110101000000110101011011101000011101001100110000111111000011010101011110001101110000000101111110100101110110101001011000100000110100101101010001111101111101111000101010100111001001011000010111111000110011100011011010000001111100001011000011000001110001110111100111110001100101101010000101001001110110000111100010011001110100011110000100100111110101100001110001001010100100010100010110110001001101010110101010001000110010000110000110111100111100100101010110010101000011100101000111101111110110000111110000001010101101001110101010011000000000000001101100100001010110110000000001011001101011110010010101011100010011100001101100110011101101111111100000100100100011010101 $
#135000
1!
#140000
0!
b1001110100010101101000010001101001000111111111010000100000111100011010100011100000001111010101001110000110000110000011110100011000000111000110000001001000001001001101000110011001100010000001100001010101101010110100010110000010001111000011011010100100110110011111100101100110001100111101011110010011011111101000010000001111001110110101001110100011011001011100110100100101101010001011100110111011110100100101000001111001100000001010000010010011001001010100001001000101010110011011101010110011100011110111000110011000110011100001010010101111110000101011000010101100111010101010110100001101101001000101110000110000100011001010101111001001000111111111101100000000110111100001011000011011111100110001111010100001111000000001001001011101001110101000010101111001010000010100100010101010101100101010001001100011011010110010110100011100010111000011111111101010101111111110001101011001011001000100111100110101011100100100000011101100100100001000101101000000101000100100001101100111010100010100010001100100000100111000101010010001100001011011001001010010101000011111101101111010011010100001110110101101011101010000011101111000000110100001000011001111010110010010 $
#145000
1!
#150000
0!
0#
#155000
1!
bx '
bx (
bx )
bx *
bx +
bx ,
bx -
bx .
#160000
0!
#165000
1!
#170000
0!
#175000
1!
#180000
0!
b0 5
#185000
1!
b1011011 '
b0 (
#190000
0!
1%
b100010001000011000000000101000111111101010111000010010001110010100010000011101000001000000000000000000001010001000000000000000010101000000000000000000000001100000000000001010100000000010100010000000000110100001011110000000001101100110001011011011000000100000000001111110001010001001110010000000000000000111110010110000110111101010101000000000001100110111000000000000000000000 &
b10000 3
b1 5
b11 6
#195000
1!
#200000
0!
b10110101101100000000000000000000000011100111100111100010000011101101001000110000000001010010011111101001111001111101001010100000000000000000101001100101101000000000001001111010110110101110000000000000000011100110000000000000000000000000111010111110100100000000011000100000000000000000111000000000000011111001001101100000000010101001001010110000000000100000000011100110100100100101 &
b10000 3
b10 5
b11 6
#205000
1!
b110101 )
b0 *
#210000
0!
b111110000000001101011111101010000000001110011010001010000100101010001111100111111101010001011001000110000010000101010000010100000000000001010000100010000001100000000000000001100010100100011000000001110001011110011011111010011010001100011101001110000000000000010011010110000000000000000000000001001100110010110000000001010011111110101100001101000100110000100 &
b10000 3
b11 5
b11 6
#215000
1!
#220000
0!
b111010010010110011001011111111000101101111010111000000000000000000001010111110001001010100100011110000111000001101110111011101101001010000000000000000000000000011000111110111010010010000000000010110100000000000000000000111100100100110000110000000000000000011010000101110000000000000101101101111001011001111011111111001100000000000000000001111011111111011001011101001100000001000000000 &
b1 0
b1001 2
b10000 3
b1000 4
b100 5
b11 6
b10 7
b10 8
b111111101010101000100001 :
b0 ;
b100111 <
b100111 =
b1100010 ?
#225000
1!
b1001001 +
b0 ,
#230000
0!
b1001100000000000100011110101010000000000000000110101110000000011101011010110110000000011101101000000001000000110001011100011010100101000000000110001101100101111000001000000000000000011101110101001100000000011100111001001000011110000000000000010111100000001100000000000001000010101011111010000110110111000000000000000001111100110101100010011110000000000000000 &
b10 0
b1001 2
b10000 3
b1000 4
b101 5
b11 6
b10 7
b10 8
b111111110011001111010100 :
b11101001 ;
b100111 <
b100111 =
b10111011 ?
#235000
1!
#240000
0!
b10010101011101000000010010100000011101001010111010001000000111000000000111010001111111111010101000001110000000000001100001111111100000100110110000000000000000000000000111101101110100100000000000000001101101111100001000000000000000001011010000000000000000010010000011000011010011100000000000000000000000000000000111111010000000000111001011000000000100000000000000000001010111010101101 &
b11 0
b1001 2
b10000 3
b1000 4
b110 5
b11 6
b10 7
b10 8
b111111111101000110001101 :
b0 ;
b100111 <
b100111 =
b100011000 ?
#245000
1!
b1000101 -
b0 .
